atlas_actris/__call_atlas_interactive__.py
atlas_actris/__get_T_P_profiles_from_cloudnet__.py
atlas_actris/__get_config_file_from_scc_hoi__.py
atlas_actris/__init__.py
atlas_actris/__master__.py
atlas_actris/__master_intercomparison__.py
atlas_actris/__nsf_calculator__.py
atlas_actris/__nsf_calculator_updated__.py
atlas_actris/__scc_api_parser__.py
atlas_actris/__screen_bad_files__.py
atlas_actris/__signal_comparison__.py
atlas_actris/__signal_gluing__.py
atlas_actris/__signal_testing__.py
atlas_actris/__signal_viewer__.py
atlas_actris/version.py
atlas_actris/helper_functions/__init__.py
atlas_actris/helper_functions/__parse_init_file__.py
atlas_actris/helper_functions/caller_utils.py
atlas_actris/helper_functions/caller_utils_old.py
atlas_actris/helper_functions/caller_utils_old_old.py
atlas_actris/helper_functions/cleaner.py
atlas_actris/helper_functions/comparison_utils.py
atlas_actris/helper_functions/error_classes.py
atlas_actris/helper_functions/get_scc_config.py
atlas_actris/helper_functions/parse_caller_args.py
atlas_actris/helper_functions/parse_intercomparison_args.py
atlas_actris/helper_functions/parse_master_args.py
atlas_actris/helper_functions/printouts.py
atlas_actris/helper_functions/processing_chain.py
atlas_actris/helper_functions/read_intercomparison_config.py
atlas_actris/helper_functions/read_master_config.py
atlas_actris/helper_functions/running_options.py
atlas_actris/helper_functions/save_ini_files.py
atlas_actris/helper_functions/testing_utils.py
atlas_actris/helper_functions/time_conversions.py
atlas_actris/helper_functions/viewer_utils.py
atlas_actris/processor/__init__.py
atlas_actris/processor/__preprocessor__.py
atlas_actris/processor/arc/__init__.py
atlas_actris/processor/arc/atmosphere.py
atlas_actris/processor/arc/constants.py
atlas_actris/processor/arc/make_gas.py
atlas_actris/processor/arc/molecular_properties.py
atlas_actris/processor/arc/raman_scattering.py
atlas_actris/processor/arc/rayleigh_brillouin.py
atlas_actris-0.6.6.dist-info/licenses/LICENSE
atlas_actris-0.6.6.dist-info/METADATA
atlas_actris-0.6.6.dist-info/WHEEL
atlas_actris-0.6.6.dist-info/entry_points.txt
atlas_actris-0.6.6.dist-info/top_level.txt
atlas_actris-0.6.6.dist-info/RECORD
