Metadata-Version: 2.4
Name: atlas_actris
Version: 0.6.6
Author-email: Nikolaos Siomos <nikolaos.siomos@lmu.de>, Livio Belegante <livio@inoe.ro>
License-Expression: AGPL-3.0-or-later
Project-URL: Homepage, https://github.com/nikolaos-siomos/ATLAS
Project-URL: Issues, https://github.com/nikolaos-siomos/ATLAS/issues
Classifier: Programming Language :: Python
Classifier: Programming Language :: Python :: 3
Classifier: Programming Language :: Python :: 3.9
Classifier: Operating System :: OS Independent
Requires-Python: >=3.9
License-File: LICENSE
Requires-Dist: numpy>=2.0.0
Requires-Dist: pandas>=2.2.3
Requires-Dist: xarray>=2023.6.0
Requires-Dist: netCDF4>=1.6.3
Requires-Dist: scipy>=1.13.0
Requires-Dist: matplotlib>=3.8.0
Requires-Dist: bokeh>=3.4.3
Requires-Dist: Pillow>=11.1.0
Requires-Dist: dask>=2024.8.0
Requires-Dist: requests>=2.0.0
Dynamic: license-file
